Metadata-Version: 2.1
Name: example-pkg-chun45
Version: 0.0.1
Summary: 测试发布包
Home-page: UNKNOWN
Author: wangchun
Author-email: 1164004116@qq.com
License: UNKNOWN
Platform: UNKNOWN
Classifier: Programming Language :: Python :: 3
Classifier: License :: OSI Approved :: MIT License
Classifier: Operating System :: OS Independent
